Metadata-Version: 2.4
Name: bach-envato_downloader_api1
Version: 1.0.0
Summary: MCP server for accessing Envato Downloader Api1 API
Project-URL: Homepage, https://github.com/bachstudio/bach-envato_downloader_api1
Project-URL: Repository, https://github.com/bachstudio/bach-envato_downloader_api1
Project-URL: Documentation, https://github.com/bachstudio/bach-envato_downloader_api1#readme
Project-URL: Bug Tracker, https://github.com/bachstudio/bach-envato_downloader_api1/issues
Author: bachstudio
License: MIT License
License-File: LICENSE
Keywords: api,envato_downloader_api1,mcp,model-context-protocol
Classifier: Development Status :: 4 - Beta
Classifier: Intended Audience :: Developers
Classifier: License :: OSI Approved :: MIT License
Classifier: Programming Language :: Python :: 3
Classifier: Programming Language :: Python :: 3.10
Classifier: Programming Language :: Python :: 3.11
Classifier: Programming Language :: Python :: 3.12
Requires-Python: >=3.10
Requires-Dist: fastmcp>=2.0.0
Requires-Dist: httpx>=0.25.0
Provides-Extra: dev
Requires-Dist: black>=23.0.0; extra == 'dev'
Requires-Dist: pytest>=7.0.0; extra == 'dev'
